picflip/__init__.py
picflip/cli.py
picflip-0.1.2.dist-info/LICENSE
picflip-0.1.2.dist-info/METADATA
picflip-0.1.2.dist-info/WHEEL
picflip-0.1.2.dist-info/entry_points.txt
picflip-0.1.2.dist-info/top_level.txt
picflip-0.1.2.dist-info/RECORD
